vardautomation/__init__.py
vardautomation/_metadata.py
vardautomation/automation.py
vardautomation/binary_path.py
vardautomation/chapterisation.py
vardautomation/comp.py
vardautomation/config.py
vardautomation/exception.py
vardautomation/language.py
vardautomation/logo.txt
vardautomation/py.typed
vardautomation/render.py
vardautomation/types.py
vardautomation/utils.py
vardautomation/vpathlib.py
vardautomation/_logging/__init__.py
vardautomation/_logging/abstract.py
vardautomation/_logging/core.py
vardautomation/_logging/helpers.py
vardautomation/tooling/__init__.py
vardautomation/tooling/abstract.py
vardautomation/tooling/audio.py
vardautomation/tooling/base.py
vardautomation/tooling/misc.py
vardautomation/tooling/mux.py
vardautomation/tooling/video.py
vardautomation-1.2.4.dist-info/LICENSE
vardautomation-1.2.4.dist-info/METADATA
vardautomation-1.2.4.dist-info/WHEEL
vardautomation-1.2.4.dist-info/top_level.txt
vardautomation-1.2.4.dist-info/RECORD
