Metadata-Version: 2.1
Name: vardautomation
Version: 1.2.4
Summary: Encoding automation tools via Vapoursynth
Home-page: https://github.com/Ichunjo/vardautomation
Author: Ichunjo
Author-email: ichunjo.le.terrible@gmail.com
Classifier: Programming Language :: Python :: 3
Classifier: License :: OSI Approved :: MIT License
Classifier: Operating System :: OS Independent
Requires-Python: >=3.10
License-File: LICENSE
Requires-Dist: langcodes (~=3.3.0)
Requires-Dist: language-data (~=1.1)
Requires-Dist: loguru (~=0.6.0)
Requires-Dist: lxml (~=4.9.1)
Requires-Dist: numpy (~=1.23.5)
Requires-Dist: psutil (~=5.9.4)
Requires-Dist: pymediainfo (~=6.0.1)
Requires-Dist: pyparsebluray (~=0.1.4)
Requires-Dist: pyparsedvd (~=0.0.3)
Requires-Dist: pytimeconv (~=0.0.2)
Requires-Dist: requests (~=2.28.1)
Requires-Dist: requests-toolbelt (~=0.10.1)
Requires-Dist: rich (~=12.6.0)
Requires-Dist: typing-extensions (~=4.4.0)
Requires-Dist: vardefunc (~=0.7.0)
Requires-Dist: VapourSynth (==60)
